flamapy/metamodels/dn_metamodel/__init__.py
flamapy/metamodels/dn_metamodel/models/__init__.py
flamapy/metamodels/dn_metamodel/models/dependency_network.py
flamapy/metamodels/dn_metamodel/operations/__init__.py
flamapy/metamodels/dn_metamodel/operations/network_info.py
flamapy/metamodels/dn_metamodel/transformations/__init__.py
flamapy/metamodels/dn_metamodel/transformations/serialize_network.py
flamapy_dn-1.1.6.dist-info/LICENSE.md
flamapy_dn-1.1.6.dist-info/METADATA
flamapy_dn-1.1.6.dist-info/WHEEL
flamapy_dn-1.1.6.dist-info/top_level.txt
flamapy_dn-1.1.6.dist-info/RECORD
